privex/__init__.py
privex/exchange/Binance.py
privex/exchange/Bittrex.py
privex/exchange/CoinGecko.py
privex/exchange/Huobi.py
privex/exchange/Kraken.py
privex/exchange/SteemEngine.py
privex/exchange/__init__.py
privex/exchange/adapter_template.py
privex/exchange/base.py
privex/exchange/exceptions.py
privex/exchange/helpers.py
privex_exchange-0.2.0.dist-info/LICENSE
privex_exchange-0.2.0.dist-info/METADATA
privex_exchange-0.2.0.dist-info/WHEEL
privex_exchange-0.2.0.dist-info/top_level.txt
privex_exchange-0.2.0.dist-info/RECORD
