Metadata-Version: 2.1
Name: privex-exchange
Version: 0.2.0
Summary: A small library for querying Cryptocurrency exchanges and other price sources
Home-page: https://github.com/Privex/python-exchange
Author: Chris (Someguy123) @ Privex
Author-email: chris@privex.io
License: MIT
Platform: UNKNOWN
Classifier: Programming Language :: Python :: 3.8
Classifier: Programming Language :: Python :: 3.7
Classifier: Programming Language :: Python :: 3
Classifier: License :: OSI Approved :: MIT License
Classifier: Operating System :: OS Independent
Requires-Dist: httpx (>=0.12.0)
Requires-Dist: attrs
Requires-Dist: async-property
Requires-Dist: privex-helpers[cache] (>=2.18.0)
Requires-Dist: privex-steemengine (>=2.1.0)
Provides-Extra: dev
Requires-Dist: jupyter ; extra == 'dev'
Requires-Dist: wheel ; extra == 'dev'
Requires-Dist: setuptools ; extra == 'dev'
Requires-Dist: twine ; extra == 'dev'
Requires-Dist: privex-helpers[dev] ; extra == 'dev'
Requires-Dist: pytest ; extra == 'dev'
Requires-Dist: pytest-cov ; extra == 'dev'
Requires-Dist: coverage ; extra == 'dev'
Requires-Dist: codecov ; extra == 'dev'
Requires-Dist: pytest-asyncio ; extra == 'dev'
Requires-Dist: nest-asyncio ; extra == 'dev'
